{
  "case_id": "CASE-20251106183734-USD800.00-5CBA167A",
  "description": "PACS File Pair - Alice Smith",
  "amount": "800.00",
  "currency": "USD",
  "status": "completed",
  "created_at": "2025-11-06T18:37:34.883195",
  "pacs004_data": {
    "message_id": null,
    "transaction_id": null,
    "return_reason": null,
    "uetr": null,
    "e2e": null
  },
  "pacs008_data": {
    "message_id": "MSG-20251008-ORIG-002",
    "transaction_id": "abc12345-e89b-12d3-a456-426614174abc",
    "uetr": "abc12345-e89b-12d3-a456-426614174abc",
    "e2e": "E2EID-FCA-001",
    "amount": "800.00",
    "currency": "USD",
    "debtor_name": "Alice Smith",
    "debtor_account": "\n          ",
    "creditor_name": "Business Partner GmbH",
    "creditor_account": "\n          "
  },
  "email_data": {
    "case_id": "CASE-20251106183734-USD800.00-5CBA167A",
    "email_subject": "return of funds",
    "email_recipient": "Intelli Processing",
    "email_body": "Reference: CASE-20251106183734-USD800.00-5CBA167A\nSubject: return of funds\nTransaction reference: E2EID-FCA-001\n\n:20:E2EID-FCA-001\n:23B:CRED\n:32A:251106USD650.00\n:33B:USD650.00\n:50K:A*********h\n:52A:BOSPGBPMXXXX\n:57A:CBAAU2SXXXX\n:59A:CBAAU2SXXXX\n:71F:USD0,00\n:71F:USD0,00\n:72:/BEN/99\n/R99/MS01/MREF/E2EID-FCA-001/TEX\n/MREF/OL_REFERENCE\n/TEXT/IT/Account closed",
    "transaction_ref": "E2EID-FCA-001",
    "generated_at": "2025-11-06T18:37:34.883195"
  },
  "pacs004_content": "<?xml version=\"1.0\" encoding=\"UTF-8\"?>\n<Document xmlns=\"urn:iso:std:iso:20022:tech:xsd:pacs.004.001.12\" xmlns:xsi=\"http://www.w3.org/2001/XMLSchema-instance\">\n  <PmtRtr>\n    <GrpHdr>\n      <MsgId>MSG-20251008-002</MsgId>\n      <CreDtTm>2025-10-08T11:45:00</CreDtTm>\n      <NbOfTxs>1</NbOfTxs>\n      <SttlmInf>\n        <SttlmMtd>INDA</SttlmMtd>\n      </SttlmInf>\n    </GrpHdr>\n    <TxInf>\n      <RtrId>RET-USD-20251008-002</RtrId>\n      <OrgnlGrpInf>\n        <OrgnlMsgId>MSG-20251008-ORIG-002</OrgnlMsgId>\n        <OrgnlMsgNmId>pacs.008.001.12</OrgnlMsgNmId>\n        <OrgnlCreDtTm>2025-10-08T10:30:00</OrgnlCreDtTm>\n      </OrgnlGrpInf>\n      <OrgnlInstrId>INSTR-20251008-002</OrgnlInstrId>\n      <OrgnlEndToEndId>E2EID-FCA-001</OrgnlEndToEndId>\n      <OrgnlTxId>abc12345-e89b-12d3-a456-426614174abc</OrgnlTxId>\n      <OrgnlUETR>abc12345-e89b-12d3-a456-426614174abc</OrgnlUETR>\n      <RtrdIntrBkSttlmAmt Ccy=\"USD\">650.00</RtrdIntrBkSttlmAmt>\n      <IntrBkSttlmDt>2025-10-08</IntrBkSttlmDt>\n      <SttlmPrty>NORM</SttlmPrty>\n      <RtrdInstdAmt Ccy=\"USD\">650.00</RtrdInstdAmt>\n      <ChrgBr>DEBT</ChrgBr>\n      <RtrRsnInf>\n        <Orgtr>\n          <Nm>Commonwealth Bank of Australia</Nm>\n          <Id>\n            <OrgId>\n              <Othr>\n                <Id>CBA</Id>\n                <SchmeNm>\n                  <Cd>BANK</Cd>\n                </SchmeNm>\n              </Othr>\n            </OrgId>\n          </Id>\n        </Orgtr>\n        <Rsn>\n          <Cd>AC04</Cd>\n        </Rsn>\n        <AddtlInf>Account closed</AddtlInf>\n      </RtrRsnInf>\n      <OrgnlTxRef>\n        <IntrBkSttlmAmt Ccy=\"USD\">750.00</IntrBkSttlmAmt>\n        <IntrBkSttlmDt>2025-10-08</IntrBkSttlmDt>\n        <SttlmPrty>NORM</SttlmPrty>\n        <InstdAmt Ccy=\"USD\">750.00</InstdAmt>\n        <ChrgBr>DEBT</ChrgBr>\n        <ChrgsInf>\n          <Amt Ccy=\"USD\">35.00</Amt>\n          <Agt>\n            <FinInstnId>\n              <BICFI>DEUTDEFF</BICFI>\n            </FinInstnId>\n          </Agt>\n        </ChrgsInf>\n        <PmtTpInf>\n          <SvcLvl>\n            <Cd>SEPA</Cd>\n          </SvcLvl>\n          <LclInstrm>\n            <Cd>WIRE</Cd>\n          </LclInstrm>\n        </PmtTpInf>\n        <MndtRltdInf>\n          <MndtId>MANDATE-002</MndtId>\n          <DtOfSgntr>2025-10-01</DtOfSgntr>\n        </MndtRltdInf>\n        <RmtInf>\n          <Ustrd>Business payment</Ustrd>\n        </RmtInf>\n        <UltmtDbtr>\n          <Nm>Alice Smith</Nm>\n          <Id>\n            <OrgId>\n              <Othr>\n                <Id>2002195062</Id>\n                <SchmeNm>\n                  <Cd>ACCT</Cd>\n                </SchmeNm>\n              </Othr>\n            </OrgId>\n          </Id>\n        </UltmtDbtr>\n        <Dbtr>\n          <Nm>Alice Smith</Nm>\n          <Id>\n            <OrgId>\n              <Othr>\n                <Id>2002195062</Id>\n                <SchmeNm>\n                  <Cd>ACCT</Cd>\n                </SchmeNm>\n              </Othr>\n            </OrgId>\n          </Id>\n        </Dbtr>\n        <DbtrAcct>\n          <Id>\n            <Othr>\n              <Id>2002195062</Id>\n            </Othr>\n          </Id>\n        </DbtrAcct>\n        <DbtrAgt>\n          <FinInstnId>\n            <BICFI>CBA</BICFI>\n            <Nm>Commonwealth Bank of Australia</Nm>\n          </FinInstnId>\n        </DbtrAgt>\n        <CdtrAgt>\n          <FinInstnId>\n            <BICFI>DEUTDEFF</BICFI>\n            <Nm>Deutsche Bank</Nm>\n          </FinInstnId>\n        </CdtrAgt>\n        <Cdtr>\n          <Nm>Business Partner GmbH</Nm>\n          <Id>\n            <OrgId>\n              <Othr>\n                <Id>DE89370400440532013000</Id>\n                <SchmeNm>\n                  <Cd>IBAN</Cd>\n                </SchmeNm>\n              </Othr>\n            </OrgId>\n          </Id>\n        </Cdtr>\n        <CdtrAcct>\n          <Id>\n            <IBAN>DE89370400440532013000</IBAN>\n          </Id>\n        </CdtrAcct>\n      </OrgnlTxRef>\n    </TxInf>\n  </PmtRtr>\n</Document>\n",
  "pacs008_content": "<?xml version=\"1.0\" encoding=\"UTF-8\"?>\n<Document xmlns=\"urn:iso:std:iso:20022:tech:xsd:pacs.008.001.12\" xmlns:xsi=\"http://www.w3.org/2001/XMLSchema-instance\">\n  <FIToFICstmrCdtTrf>\n    <GrpHdr>\n      <MsgId>MSG-20251008-ORIG-002</MsgId>\n      <CreDtTm>2025-10-08T10:30:00</CreDtTm>\n      <NbOfTxs>1</NbOfTxs>\n      <SttlmInf>\n        <SttlmMtd>INDA</SttlmMtd>\n      </SttlmInf>\n    </GrpHdr>\n    <CdtTrfTxInf>\n      <PmtId>\n        <InstrId>INSTR-20251008-002</InstrId>\n        <EndToEndId>E2EID-FCA-001</EndToEndId>\n        <TxId>abc12345-e89b-12d3-a456-426614174abc</TxId>\n        <UETR>abc12345-e89b-12d3-a456-426614174abc</UETR>\n      </PmtId>\n      <IntrBkSttlmAmt Ccy=\"USD\">800.00</IntrBkSttlmAmt>\n      <IntrBkSttlmDt>2025-10-08</IntrBkSttlmDt>\n      <SttlmPrty>NORM</SttlmPrty>\n      <InstdAmt Ccy=\"USD\">800.00</InstdAmt>\n      <ChrgBr>DEBT</ChrgBr>\n      <ChrgsInf>\n        <Amt Ccy=\"USD\">35.00</Amt>\n        <Agt>\n          <FinInstnId>\n            <BICFI>DEUTDEFF</BICFI>\n          </FinInstnId>\n        </Agt>\n      </ChrgsInf>\n      <PmtTpInf>\n        <SvcLvl>\n          <Cd>SEPA</Cd>\n        </SvcLvl>\n        <LclInstrm>\n          <Cd>WIRE</Cd>\n        </LclInstrm>\n      </PmtTpInf>\n      <MndtRltdInf>\n        <MndtId>MANDATE-002</MndtId>\n        <DtOfSgntr>2025-10-01</DtOfSgntr>\n      </MndtRltdInf>\n      <RmtInf>\n        <Ustrd>Business payment</Ustrd>\n      </RmtInf>\n      <UltmtDbtr>\n        <Nm>Alice Smith</Nm>\n        <Id>\n          <OrgId>\n            <Othr>\n              <Id>2002195062</Id>\n              <SchmeNm>\n                <Cd>ACCT</Cd>\n              </SchmeNm>\n            </Othr>\n          </OrgId>\n        </Id>\n      </UltmtDbtr>\n      <Dbtr>\n        <Nm>Alice Smith</Nm>\n        <Id>\n          <OrgId>\n            <Othr>\n              <Id>2002195062</Id>\n              <SchmeNm>\n                <Cd>ACCT</Cd>\n              </SchmeNm>\n            </Othr>\n          </OrgId>\n        </Id>\n      </Dbtr>\n      <DbtrAcct>\n        <Id>\n          <Othr>\n            <Id>2002195062</Id>\n          </Othr>\n        </Id>\n      </DbtrAcct>\n      <DbtrAgt>\n        <FinInstnId>\n          <BICFI>CBA</BICFI>\n          <Nm>Commonwealth Bank of Australia</Nm>\n        </FinInstnId>\n      </DbtrAgt>\n      <CdtrAgt>\n        <FinInstnId>\n          <BICFI>DEUTDEFF</BICFI>\n          <Nm>Deutsche Bank</Nm>\n        </FinInstnId>\n      </CdtrAgt>\n      <Cdtr>\n        <Nm>Business Partner GmbH</Nm>\n        <Id>\n          <OrgId>\n            <Othr>\n              <Id>DE89370400440532013000</Id>\n              <SchmeNm>\n                <Cd>IBAN</Cd>\n              </SchmeNm>\n            </Othr>\n          </OrgId>\n        </Id>\n      </Cdtr>\n      <CdtrAcct>\n        <Id>\n          <IBAN>DE89370400440532013000</IBAN>\n        </Id>\n      </CdtrAcct>\n    </CdtTrfTxInf>\n  </FIToFICstmrCdtTrf>\n</Document>\n",
  "pacs004_filename": "test_scenario_2_fca_refund.xml",
  "pacs008_filename": "test_scenario_2_fca_refund_pacs008.xml",
  "run_id": "fff6d20f-e1c6-489a-847d-e2dfb0e3a722",
  "processed_at": "2025-11-06T18:38:27.721667"
}